{
    "AWS": {
        "ACCESS_ID": "XXXXXXXXXXXXXXXXXX",
        "SECRET_KEY": "XXXXXXXXXXXXXXXXXX",
        "ACCOUNT_ID": "XXXXXXXXXXXXXXXXXX",
        "DEFAULT_REGION": "XXXXXXXXXXXXXXXXXX"
    },
    "LED_SIGN": {
        "QUEUE_NAME": "XXXXXXXXXXXXXXXXXX",
        "IP": "XXXXXXXXXXXXXXXXXX"
    },
    "PRINTING": {
        "QUEUE_NAME": "XXXXXXXXXXXXXXXXXX",
        "BUCKET_NAME": "XXXXXXXXXXXXXXXXXX",
        "FETCH_INTERVAL_SECONDS": "XXXXXXXXXXXXXXXXXX",
        "INFLUX_URL": "XXXXXXXXXXXXXXXXXX",
        "LEFT": {
            "ENABLED": true,
            "NAME": "XXXXXXXXXXXXXXXXXX",
            "IP": "XXXXXXXXXXXXXXXXXX",
            "LPD_URL": "XXXXXXXXXXXXXXXXXX"
        },
        "RIGHT": {
            "ENABLED": true,
            "NAME": "XXXXXXXXXXXXXXXXXX",
            "IP": "XXXXXXXXXXXXXXXXXX",
            "LPD_URL": "XXXXXXXXXXXXXXXXXX"
        }
    }
}
